swoopyui/__init__.py
swoopyui/protocol.py
swoopyui/swoopyui.py
swoopyui/view.py
swoopyui/UIkits/__init__.py
swoopyui/assets/__init__.py
swoopyui/assets/swoopyui.zip
swoopyui/assets/swoopyui_agent.zip
swoopyui/assets/swoopyui_menubarextra.zip
swoopyui/tools/__init__.py
swoopyui/tools/check_if_mac.py
swoopyui/tools/check_platform.py
swoopyui/tools/get_free_port.py
swoopyui/tools/on_action.py
swoopyui/tools/pyinstaller_check.py
swoopyui/tools/run_swiftUI.py
swoopyui/tools/run_swiftUI_ios.py
swoopyui/tools/run_target.py
swoopyui/tools/swoopyui_host.py
swoopyui/tools/unzip_assets.py
swoopyui/views/__init__.py
swoopyui/views/button.py
swoopyui/views/colorview.py
swoopyui/views/contextmenu.py
swoopyui/views/elevatedbutton.py
swoopyui/views/geometryreader.py
swoopyui/views/hstack.py
swoopyui/views/icon.py
swoopyui/views/label.py
swoopyui/views/labeledbutton.py
swoopyui/views/list.py
swoopyui/views/menu.py
swoopyui/views/navigationlink.py
swoopyui/views/navigationsplitview.py
swoopyui/views/navigationstack.py
swoopyui/views/scrollingtabview.py
swoopyui/views/scrollview.py
swoopyui/views/sheet.py
swoopyui/views/spacer.py
swoopyui/views/subview.py
swoopyui/views/subviewparent.py
swoopyui/views/text.py
swoopyui/views/textbutton.py
swoopyui/views/textfield.py
swoopyui/views/toggle.py
swoopyui/views/videoplayer.py
swoopyui/views/vstack.py
swoopyui/views/zstack.py
swoopyui/views/shapes/__init__.py
swoopyui/views/shapes/roundedrectangleshape.py
swoopyui_app/__init__.py
swoopyui_app/main.py
swoopyui-2.7.dist-info/LICENSE
swoopyui-2.7.dist-info/METADATA
swoopyui-2.7.dist-info/WHEEL
swoopyui-2.7.dist-info/top_level.txt
swoopyui-2.7.dist-info/RECORD
