Metadata-Version: 2.1
Name: swoopyui
Version: 2.7
Summary: A python library that allow you to build swiftUI apps using python.
Home-page: https://github.com/SKbarbon/swoopyui
Author: SKbarbon
Classifier: Programming Language :: Python :: 3
Classifier: Operating System :: MacOS :: MacOS X
License-File: LICENSE
Requires-Dist: flask
Requires-Dist: requests
